payture/__init__.py
payture/api.py
payture/cardinfo.py
payture/constants.py
payture/digitalwallet.py
payture/encodedata.py
payture/ewallet.py
payture/inpay.py
payture/merchant.py
payture/paytureresponse.py
payture/transaction.py
payture-0.0.17.dist-info/DESCRIPTION.rst
payture-0.0.17.dist-info/METADATA
payture-0.0.17.dist-info/RECORD
payture-0.0.17.dist-info/WHEEL
payture-0.0.17.dist-info/metadata.json
payture-0.0.17.dist-info/top_level.txt
